butterfly.v
// 
// butterfly.v — Single Butterfly Unit for 8-point NTT
//
// Computes the Cooley-Tukey DIT butterfly:
//   u = (a + b*w) mod q
//   v = (a - b*w) mod q
//
// Parameters: q=17, so all values fit in 5 bits; products fit in 9 bits.
// 

module butterfly #(
    parameter DATA_WIDTH = 5,   // ceil(log2(q))  — values 0..16
    parameter Q          = 17
)(
    input  wire [DATA_WIDTH-1:0] a,
    input  wire [DATA_WIDTH-1:0] b,
    input  wire [DATA_WIDTH-1:0] w,   // twiddle factor
    output wire [DATA_WIDTH-1:0] u,   // a + b*w  mod q
    output wire [DATA_WIDTH-1:0] v    // a - b*w  mod q
);

    // 
    // Step 1: Modular multiplication  bw = b*w mod q
    // For small q (17) the product b*w <= 16*16 = 256, fits in 9 bits.
    // We reduce with a simple subtraction loop -- acceptable for q=17.
    // For large primes, replace with Barrett or Montgomery reduction.
    // 
    wire [8:0] prod = b * w;

    // Reduce: prod mod 17.  Max value 256, so at most 15 subtractions of 17.
    // We use a combinational divide-by-constant approach: prod - (prod/q)*q
    // Since q=17 is constant, synthesis will optimise this into a small LUT.
    wire [8:0] bw = prod - (prod / Q) * Q;

    // 
    // Step 2: Modular addition   u = (a + bw) mod q
    // 
    wire [5:0] sum = a + bw[4:0];
    assign u = (sum >= Q) ? (sum - Q) : sum[DATA_WIDTH-1:0];

    // 
    // Step 3: Modular subtraction  v = (a - bw) mod q
    // Add q before subtracting to keep result non-negative.
    // 
    wire [5:0] diff = a + Q - bw[4:0];
    assign v = (diff >= Q) ? (diff - Q) : diff[DATA_WIDTH-1:0];

endmodule

twiddle_rom.v
// 
// twiddle_rom.v — ROM storing precomputed twiddle factors
//
// Twiddle factors: w^k mod q for k = 0..3, where w=9, q=17
//   w^0 = 1
//   w^1 = 9
//   w^2 = 13   (81 mod 17)
//   w^3 = 15   (729 mod 17)
//
// The NTT controller provides an index (0..3); this ROM returns the value.
//

module twiddle_rom #(
    parameter DATA_WIDTH = 5,
    parameter ADDR_WIDTH = 2    // 4 entries: indices 0..3
)(
    input  wire [ADDR_WIDTH-1:0] addr,
    output reg  [DATA_WIDTH-1:0] data
);

    // Synchronous-read not needed — purely combinational ROM.
    always @(*) begin
        case (addr)
            2'd0: data = 5'd1;   // w^0 = 1
            2'd1: data = 5'd9;   // w^1 = 9
            2'd2: data = 5'd13;  // w^2 = 13
            2'd3: data = 5'd15;  // w^3 = 15
            default: data = 5'd0;
        endcase
    end

endmodule

ntt_top.v
// 
// ntt_top.v — 8-point NTT Accelerator (iterative, single butterfly)
//
// Algorithm: Cooley-Tukey DIT (decimation-in-time) with bit-reversal input.
// Parameters: n=8, q=17, ω=9
//

//
// FSM states:
//   IDLE       → waiting for start
//   LOAD       → copy input coefficients into RAM (with bit-reversal)
//   COMPUTE    → iterate stages 1..3, each with n/2=4 butterfly operations
//   DONE       → assert done, hold output
//
// Bit-reversal of addresses (n=8, 3-bit):
//   0→0, 1→4, 2→2, 3→6, 4→1, 5→5, 6→3, 7→7
// 

module ntt_top #(
    parameter N          = 8,
    parameter DATA_WIDTH = 5,   // ceil(log2(17))
    parameter Q          = 17,
    parameter LOG2N      = 3    // log2(8)
)(
    input  wire                        clk,
    input  wire                        rst_n,
    input  wire                        start,
    input  wire [DATA_WIDTH*N-1:0]     coeff_in,   // 8 packed coefficients
    output wire [DATA_WIDTH*N-1:0]     coeff_out,  // 8 packed results
    output reg                         done
);

    // 
    // Data RAM — 8 locations × 5 bits
    // Implemented as register file for simplicity (dual-read, dual-write).
    // 
    reg [DATA_WIDTH-1:0] ram [0:N-1];

    // 
    // Twiddle ROM
    // 
    reg  [1:0]           tw_addr;
    wire [DATA_WIDTH-1:0] tw_data;

    twiddle_rom trom (
        .addr(tw_addr),
        .data(tw_data)
    );

    // 
    // Butterfly unit
    // 
    reg  [DATA_WIDTH-1:0] bf_a, bf_b, bf_w;
    wire [DATA_WIDTH-1:0] bf_u, bf_v;

    butterfly #(.DATA_WIDTH(DATA_WIDTH), .Q(Q)) bfly (
        .a(bf_a), .b(bf_b), .w(bf_w),
        .u(bf_u), .v(bf_v)
    );

    // 
    // FSM
    // 
    localparam IDLE    = 2'd0,
               LOAD    = 2'd1,
               COMPUTE = 2'd2,
               DONE_ST = 2'd3;

    reg [1:0]  state;
    reg [2:0]  cnt;        // general counter (load: 0..7; compute: 0..3)
    reg [1:0]  stage;      // 1..3

    //  Bit-reversal lookup (3-bit reverse) 
    function [2:0] bit_rev3;
        input [2:0] x;
        begin
            bit_rev3 = {x[0], x[1], x[2]};
        end
    endfunction

    //  Address pair and twiddle index for butterfly cnt in stage s 
    // For DIT stage s (1-based):
    //   stride  = 2^s
    //   half    = 2^(s-1)
    //   group   = cnt / half          (which stride-group)
    //   k       = cnt % half          (offset within group)
    //   addr_a  = group*stride + k
    //   addr_b  = addr_a + half
    //   twiddle = k * (n / stride) = k << (log2n - s)
    //             capped at n/2-1 since ROM has 4 entries

    reg [2:0] addr_a_r, addr_b_r;
    reg [1:0] tw_idx_r;

    always @(*) begin
        case (stage)
            2'd1: begin
                // stride=2, half=1 — cnt in 0..3
                // group=cnt, k=0
                // addr_a = cnt*2, addr_b = cnt*2+1, twiddle = 0
                addr_a_r = {cnt[1:0], 1'b0};     // cnt*2
                addr_b_r = {cnt[1:0], 1'b1};     // cnt*2+1
                tw_idx_r = 2'd0;                  // w^0 = 1
            end
            2'd2: begin
                // stride=4, half=2 — cnt in 0..3
                // group = cnt>>1, k = cnt&1
                // addr_a = group*4 + k, addr_b = addr_a+2, twiddle = k*2
                addr_a_r = {cnt[1], 1'b0, cnt[0]};   // group*4 + k
                addr_b_r = {cnt[1], 1'b1, cnt[0]};   // addr_a + 2
                tw_idx_r = {cnt[0], 1'b0};            // k*2 (0 or 2)
            end
            default: begin // stage 3
                // stride=8, half=4 — cnt in 0..3
                // group=0, k=cnt
                // addr_a = cnt, addr_b = cnt+4, twiddle = cnt
                addr_a_r = {1'b0, cnt[1:0]};
                addr_b_r = {1'b1, cnt[1:0]};
                tw_idx_r = cnt[1:0];
            end
        endcase
    end

    // 
    // FSM sequential logic
    // 
    integer i;

    always @(posedge clk or negedge rst_n) begin
        if (!rst_n) begin
            state <= IDLE;
            done  <= 1'b0;
            cnt   <= 3'd0;
            stage <= 2'd0;
        end else begin
            case (state)
                // IDLE 
                IDLE: begin
                    done <= 1'b0;
                    if (start) begin
                        cnt   <= 3'd0;
                        state <= LOAD;
                    end
                end

                // LOAD: write bit-reversed inputs into RAM 
                LOAD: begin
                    ram[bit_rev3(cnt[2:0])] <= coeff_in[(cnt*DATA_WIDTH) +: DATA_WIDTH];
                    if (cnt == 3'd7) begin
                        cnt   <= 3'd0;
                        stage <= 2'd1;
                        state <= COMPUTE;
                    end else begin
                        cnt <= cnt + 1;
                    end
                end

                // COMPUTE: one butterfly per cycle 
                COMPUTE: begin
                    // Latch twiddle and data into butterfly inputs
                    tw_addr <= tw_idx_r;
                    bf_a    <= ram[addr_a_r];
                    bf_b    <= ram[addr_b_r];
                    bf_w    <= tw_data;

                    // Write-back results (combinational butterfly — results
                    // available same cycle we read tw_data, but tw_data is
                    // based on tw_addr set THIS cycle, so we need one cycle
                    // of latency — handled by the register stage below)
                    //
                    // To avoid the latency, we pre-fetch tw_data combinatorially
                    // using addr_a_r/addr_b_r/tw_idx_r before the register.
                    // Since twiddle_rom is combinational, tw_data reflects
                    // tw_addr from LAST cycle. We therefore use a 2-phase
                    // approach: fetch twiddle this cycle, write back next.
                    // We track this with a "write-back pending" register.
                    //
                    // Simpler alternative used here: connect tw_addr directly
                    // to tw_idx_r (combinational), and bf_w to tw_data (also
                    // combinational), so everything is one-cycle.

                    ram[addr_a_r] <= bf_u;
                    ram[addr_b_r] <= bf_v;

                    if (cnt == 3'd3) begin
                        cnt <= 3'd0;
                        if (stage == 2'd3) begin
                            state <= DONE_ST;
                        end else begin
                            stage <= stage + 1;
                        end
                    end else begin
                        cnt <= cnt + 1;
                    end
                end

                // DONE 
                DONE_ST: begin
                    done  <= 1'b1;
                    state <= IDLE;
                end

                default: state <= IDLE;
            endcase
        end
    end

    // Combinational twiddle fetch (ROM is async read)
    always @(*) begin
        tw_addr = tw_idx_r;
        bf_w    = tw_data;
        bf_a    = ram[addr_a_r];
        bf_b    = ram[addr_b_r];
    end

    // 
    // Pack RAM output
    // 
    genvar g;
    generate
        for (g = 0; g < N; g = g + 1) begin : pack_out
            assign coeff_out[g*DATA_WIDTH +: DATA_WIDTH] = ram[g];
        end
    endgenerate

endmodule

tb_ntt.v
// 
// tb_ntt.v — Testbench for 8-point NTT Accelerator
// Uses to load hex test vectors from files.
// 
`timescale 1ns/1ps

module tb_ntt;

    localparam N          = 8;
    localparam DATA_WIDTH = 5;
    localparam Q          = 17;

    reg                     clk, rst_n, start;
    reg  [DATA_WIDTH*N-1:0] coeff_in;
    wire [DATA_WIDTH*N-1:0] coeff_out;
    wire                    done;

    ntt_top #(.N(N),.DATA_WIDTH(DATA_WIDTH),.Q(Q),.LOG2N(3)) dut (
        .clk(clk),.rst_n(rst_n),.start(start),
        .coeff_in(coeff_in),.coeff_out(coeff_out),.done(done)
    );

    initial clk = 0;
    always #5 clk = ~clk;

    // Storage for test vectors
    reg [DATA_WIDTH-1:0] inp_mem  [0:N-1];
    reg [DATA_WIDTH-1:0] exp_mem  [0:N-1];
    reg [DATA_WIDTH-1:0] got      [0:N-1];

    integer i, pass_count, fail_count, cycle;
    reg test_ok;

    // Pack helper
    task pack_input;
        integer k;
        begin
            coeff_in = 0;
            for (k = 0; k < N; k = k + 1)
                coeff_in[k*DATA_WIDTH +: DATA_WIDTH] = inp_mem[k];
        end
    endtask

    // Unpack helper
    task unpack_output;
        integer k;
        begin
            for (k = 0; k < N; k = k + 1)
                got[k] = coeff_out[k*DATA_WIDTH +: DATA_WIDTH];
        end
    endtask

    task run_test_vec;
        input [255:0] in_file, exp_file;
        input integer test_id;
        begin
            $readmemh(in_file,  inp_mem);
            $readmemh(exp_file, exp_mem);
            pack_input;

            $write("Test %0d | in:  [", test_id);
            for (i=0;i<N;i=i+1) $write("%2d%s",inp_mem[i],(i<N-1)?",":"");
            $write("]\n");

            // Reset
            @(negedge clk); rst_n=0; start=0;
            @(negedge clk); @(negedge clk); rst_n=1;
            @(negedge clk);
            // Start
            start=1; @(negedge clk); start=0;

            // Wait for done
            cycle=0;
            while (!done && cycle < 200) begin
                @(posedge clk); #1; cycle=cycle+1;
            end

            if (!done) begin
                $display("  TIMEOUT!"); fail_count=fail_count+1;
            end else begin
                unpack_output;
                $write("        | exp: [");
                for (i=0;i<N;i=i+1) $write("%2d%s",exp_mem[i],(i<N-1)?",":"");
                $write("]\n");
                $write("        | got: [");
                for (i=0;i<N;i=i+1) $write("%2d%s",got[i],(i<N-1)?",":"");
                $write("]");

                test_ok=1;
                for (i=0;i<N;i=i+1)
                    if (got[i] !== exp_mem[i]) test_ok=0;

                if (test_ok) begin
                    $write("  PASS\n"); pass_count=pass_count+1;
                end else begin
                    $write("  FAIL\n"); fail_count=fail_count+1;
                    for (i=0;i<N;i=i+1)
                        if (got[i] !== exp_mem[i])
                            $display("  Mismatch[%0d]: exp=%0d got=%0d",i,exp_mem[i],got[i]);
                end
            end
            $write("\n");
        end
    endtask

    initial begin
        $display("=================================================");
        $display("  8-point NTT Accelerator — Simulation Results");
        $display("  n=8  q=17  omega=9");
        $display("=================================================\n");
        rst_n=0; start=0; coeff_in=0; pass_count=0; fail_count=0;
        repeat(4) @(negedge clk); rst_n=1;

        run_test_vec("input_0.hex","expected_0.hex",0);
        run_test_vec("input_1.hex","expected_1.hex",1);
        run_test_vec("input_2.hex","expected_2.hex",2);
        run_test_vec("input_3.hex","expected_3.hex",3);

        $display("=================================================");
        $display("  %0d PASSED  |  %0d FAILED  (of 4 tests)", pass_count, fail_count);
        $display("=================================================");
        if (fail_count==0) $display("  ALL TESTS PASSED");
        $finish;
    end

    initial begin
        $dumpfile("ntt_sim.vcd");
        $dumpvars(0, tb_ntt);
    end
endmodule

ntt_sim.vcd
$date
	Mon May 25 09:07:33 2026
$end
$version
	Icarus Verilog
$end
$timescale
	1ps
$end
$scope module tb_ntt $end
$var wire 1 ! done $end
$var wire 40 " coeff_out [39:0] $end
$var reg 1 # clk $end
$var reg 40 $ coeff_in [39:0] $end
$var reg 1 % rst_n $end
$var reg 1 & start $end
$var reg 1 ' test_ok $end
$var integer 32 ( cycle [31:0] $end
$var integer 32 ) fail_count [31:0] $end
$var integer 32 * i [31:0] $end
$var integer 32 + pass_count [31:0] $end
$scope module dut $end
$var wire 1 # clk $end
$var wire 40 , coeff_in [39:0] $end
$var wire 1 % rst_n $end
$var wire 1 & start $end
$var wire 5 - tw_data [4:0] $end
$var wire 40 . coeff_out [39:0] $end
$var wire 5 / bf_v [4:0] $end
$var wire 5 0 bf_u [4:0] $end
$var reg 3 1 addr_a_r [2:0] $end
$var reg 3 2 addr_b_r [2:0] $end
$var reg 5 3 bf_a [4:0] $end
$var reg 5 4 bf_b [4:0] $end
$var reg 5 5 bf_w [4:0] $end
$var reg 3 6 cnt [2:0] $end
$var reg 1 ! done $end
$var reg 2 7 stage [1:0] $end
$var reg 2 8 state [1:0] $end
$var reg 2 9 tw_addr [1:0] $end
$var reg 2 : tw_idx_r [1:0] $end
$scope function bit_rev3 $end
$var reg 3 ; x [2:0] $end
$upscope $end
$scope begin pack_out[0] $end
$upscope $end
$scope begin pack_out[1] $end
$upscope $end
$scope begin pack_out[2] $end
$upscope $end
$scope begin pack_out[3] $end
$upscope $end
$scope begin pack_out[4] $end
$upscope $end
$scope begin pack_out[5] $end
$upscope $end
$scope begin pack_out[6] $end
$upscope $end
$scope begin pack_out[7] $end
$upscope $end
$scope module bfly $end
$var wire 5 < a [4:0] $end
$var wire 5 = b [4:0] $end
$var wire 5 > w [4:0] $end
$var wire 5 ? v [4:0] $end
$var wire 5 @ u [4:0] $end
$var wire 6 A sum [5:0] $end
$var wire 9 B prod [8:0] $end
$var wire 6 C diff [5:0] $end
$var wire 9 D bw [8:0] $end
$upscope $end
$scope module trom $end
$var wire 2 E addr [1:0] $end
$var reg 5 F data [4:0] $end
$upscope $end
$upscope $end
$scope task pack_input $end
$var integer 32 G k [31:0] $end
$upscope $end
$scope task run_test_vec $end
$var reg 256 H exp_file [255:0] $end
$var reg 256 I in_file [255:0] $end
$var integer 32 J test_id [31:0] $end
$upscope $end
$scope task unpack_output $end
$var integer 32 K k [31:0] $end
$upscope $end
$upscope $end
$enddefinitions $end
#0
$dumpvars
bx K
bx J
bx I
bx H
bx G
b1 F
b0 E
bx D
bx C
bx B
bx A
bx @
bx ?
b1 >
bx =
bx <
bx ;
b0 :
b0 9
b0 8
b0 7
b0 6
b1 5
bx 4
bx 3
b100 2
b0 1
bx 0
bx /
bx .
b1 -
b0 ,
b0 +
bx *
b0 )
bx (
x'
0&
0%
b0 $
0#
bx "
0!
$end
#5000
1#
#10000
0#
#15000
1#
#20000
0#
#25000
1#
#30000
0#
#35000
1#
#40000
b1000 *
b100000111001100010100100000110001000001 $
b100000111001100010100100000110001000001 ,
b1000 G
b0 J
b110010101111000011100000110010101100011011101000110010101100100010111110011000000101110011010000110010101111000 H
b110100101101110011100000111010101110100010111110011000000101110011010000110010101111000 I
1%
0#
#45000
1#
#50000
0%
0#
#55000
1#
#60000
0#
#65000
1#
#70000
1%
0#
#75000
1#
#80000
1&
0#
#85000
b1 8
1#
#90000
b0 (
0&
0#
#95000
b1001 5
b1001 >
b1001 -
b1001 F
b1 9
b1 E
b1 :
b101 2
b1 1
bx 3
bx <
b1 6
bx00001 "
bx00001 .
b0 ;
1#
#96000
b1 (
#100000
0#
#105000
b1101 5
b1101 >
b1101 -
b1101 F
b10 9
b10 E
b10 :
b110 2
b10 1
b10 6
bx00010xxxxxxxxxxxxxxx00001 "
bx00010xxxxxxxxxxxxxxx00001 .
b1 ;
1#
#106000
b10 (
#110000
0#
#115000
b1111 5
b1111 >
b1111 -
b1111 F
b11 9
b11 E
b11 :
b111 2
b11 1
bx 3
bx <
b11 6
bx00010xxxxx00011xxxxx00001 "
bx00010xxxxx00011xxxxx00001 .
b10 ;
1#
#116000
b11 (
#120000
0#
#125000
b10000 /
b10000 ?
b11 0
b11 @
b10000 C
b11 A
b1 5
b1 >
b10 D
b1 -
b1 F
b10 B
b10 4
b10 =
b1 3
b1 <
b0 9
b0 E
b0 :
b100 2
b0 1
b100 6
bx00100xxxxx00010xxxxx00011xxxxx00001 "
bx00100xxxxx00010xxxxx00011xxxxx00001 .
b11 ;
1#
#126000
b100 (
#130000
0#
#135000
bx 0
bx @
bx /
bx ?
b1001 5
b1001 >
bx D
bx C
b1001 -
b1001 F
bx B
bx 4
bx =
bx A
b101 3
b101 <
b1 9
b1 E
b1 :
b101 2
b1 1
b101 6
bx00100xxxxx00010xxxxx000110010100001 "
bx00100xxxxx00010xxxxx000110010100001 .
b100 ;
1#
#136000
b101 (
#140000
0#
#145000
b10 /
b10 ?
b100 0
b100 @
b1101 5
b1101 >
b10011 C
b1101 -
b1101 F
b100 A
b11 3
b11 <
b10 9
b10 E
b1 D
b10 :
b110 2
b10 1
b110100 B
b100 4
b100 =
b110 6
bx001000011000010xxxxx000110010100001 "
bx001000011000010xxxxx000110010100001 .
b101 ;
1#
#146000
b110 (
#150000
0#
#155000
bx 0
bx @
bx /
bx ?
b1111 5
b1111 >
bx D
bx C
b1111 -
b1111 F
bx B
bx 4
bx =
bx A
b111 3
b111 <
b11 9
b11 E
b11 :
b111 2
b11 1
b111 6
bx00100001100001000111000110010100001 "
bx00100001100001000111000110010100001 .
b110 ;
1#
#156000
b111 (
#160000
0#
#165000
b1101 /
b1101 ?
b110 0
b110 @
b1 5
b1 >
b1101 C
b1 -
b1 F
b110 A
b1 3
b1 <
b0 9
b0 E
b101 D
b0 :
b1 2
b0 1
b101 B
b101 4
b101 =
b10 8
b1 7
b0 6
b100000100001100001000111000110010100001 "
b100000100001100001000111000110010100001 .
b111 ;
1#
#166000
b1000 (
#170000
0#
#175000
b1010 0
b1010 @
b1101 /
b1101 ?
b111 D
b1101 C
b11 2
b10 1
b111 B
b111 4
b111 =
b1010 A
b11 3
b11 <
b1 6
b100000100001100001000111000110110100110 "
b100000100001100001000111000110110100110 .
1#
#176000
b1001 (
#180000
0#
#185000
b1101 /
b1101 ?
b1000 0
b1000 @
b110 D
b1101 C
b101 2
b100 1
b110 B
b110 4
b110 =
b1000 A
b10 3
b10 <
b10 6
b100000100001100001001101010100110100110 "
b100000100001100001001101010100110100110 .
1#
#186000
b1010 (
#190000
0#
#195000
b1100 0
b1100 @
b1101 /
b1101 ?
b1000 D
b1101 C
b111 2
b110 1
b1000 B
b1000 4
b1000 =
b1100 A
b100 3
b100 <
b11 6
b100000100011010100001101010100110100110 "
b100000100011010100001101010100110100110 .
1#
#196000
b1011 (
#200000
0#
#205000
b1101 /
b1101 ?
b10000 0
b10000 @
b1010 D
b1101 C
b10 2
b0 1
b1010 B
b1010 4
b1010 =
b10000 A
b110 3
b110 <
b10 7
b0 6
b110101100011010100001101010100110100110 "
b110101100011010100001101010100110100110 .
1#
#206000
b1100 (
#210000
0#
#215000
b1101 5
b1101 >
b1110 /
b1110 ?
b1101 -
b1101 F
b1100 0
b1100 @
b10 9
b10 E
b10000 D
b1110 C
b10 :
b11 2
b1 1
b10101001 B
b1101 4
b1101 =
b11101 A
b1101 3
b1101 <
b1 6
b110101100011010100001101011010110110000 "
b110101100011010100001101011010110110000 .
1#
#216000
b1101 (
#220000
0#
#225000
b1101 /
b1101 ?
b1 5
b1 >
b1 -
b1 F
b11 0
b11 @
b0 9
b0 E
b1100 D
b1101 C
b0 :
b110 2
b100 1
b1100 B
b1100 4
b1100 =
b10100 A
b1000 3
b1000 <
b10 6
b110101100011010100001110011010110010000 "
b110101100011010100001110011010110010000 .
1#
#226000
b1110 (
#230000
0#
#235000
b1110 /
b1110 ?
b1101 5
b1101 >
b1101 -
b1101 F
b1100 0
b1100 @
b10 9
b10 E
b10000 D
b1110 C
b10 :
b111 2
b101 1
b10101001 B
b1101 4
b1101 =
b11101 A
b1101 3
b1101 <
b11 6
b110101101011010001101110011010110010000 "
b110101101011010001101110011010110010000 .
1#
#236000
b1111 (
#240000
0#
#245000
b1101 /
b1101 ?
b1 5
b1 >
b1 -
b1 F
b10 0
b10 @
b0 9
b0 E
b11 D
b11110 C
b0 :
b100 2
b0 1
b11 B
b11 4
b11 =
b10011 A
b10000 3
b10000 <
b11 7
b0 6
b111001101011000001101110011010110010000 "
b111001101011000001101110011010110010000 .
1#
#246000
b10000 (
#250000
0#
#255000
b1001 5
b1001 >
b110 /
b110 ?
b1001 -
b1001 F
b1 0
b1 @
b1 9
b1 E
b110 D
b10111 C
b1 :
b101 2
b1 1
b1101100 B
b1100 4
b1100 =
b10010 A
b1100 3
b1100 <
b1 6
b111001101011000110101110011010110000010 "
b111001101011000110101110011010110000010 .
1#
#256000
b10001 (
#260000
0#
#265000
b1101 5
b1101 >
b1110 /
b1110 ?
b1101 -
b1101 F
b1100 0
b1100 @
b10 9
b10 E
b10000 D
b1110 C
b10 :
b110 2
b10 1
b10101001 B
b1101 4
b1101 =
b11101 A
b1101 3
b1101 <
b10 6
b111001101001100110101110011010000100010 "
b111001101001100110101110011010000100010 .
1#
#266000
b10010 (
#270000
0#
#275000
b1000 /
b1000 ?
b1111 5
b1111 >
b1111 -
b1111 F
b11 0
b11 @
b11 9
b11 E
b110 D
b11001 C
b11 :
b111 2
b11 1
b11010010 B
b1110 4
b1110 =
b10100 A
b1110 3
b1110 <
b11 6
b111001110001100110101110011000000100010 "
b111001110001100110101110011000000100010 .
1#
#276000
b10011 (
#280000
0#
#285000
b1 5
b1 >
b110 /
b110 ?
b1 -
b1 F
b1111 0
b1111 @
b0 9
b0 E
b1101 D
b110 C
b0 :
b100 2
b0 1
b1101 B
b1101 4
b1101 =
b1111 A
b10 3
b10 <
b11 8
b0 6
b100001110001100110100011011000000100010 "
b100001110001100110100011011000000100010 .
1#
#286000
b10100 (
#290000
0#
#295000
b0 8
1!
1#
#296000
b1000 G
b11000010010010010100001001000000100011 $
b11000010010010010100001001000000100011 ,
b1 J
b110010101111000011100000110010101100011011101000110010101100100010111110011000100101110011010000110010101111000 H
b110100101101110011100000111010101110100010111110011000100101110011010000110010101111000 I
b1 +
1'
b1000 *
b1000 K
b10101 (
#300000
b0 7
0!
0%
0#
#305000
1#
#310000
0#
#315000
1#
#320000
1%
0#
#325000
1#
#330000
1&
0#
#335000
b1 8
1#
#340000
b0 (
0&
0#
#345000
b1111 /
b1111 ?
b1001 5
b1001 >
b100 0
b100 @
b11 D
b1001 -
b1001 F
b110110 B
b110 4
b110 =
b1 9
b1 E
b1111 C
b1 :
b101 2
b1 1
b100 A
b1 3
b1 <
b1 6
b100001110001100110100011011000000100011 "
b100001110001100110100011011000000100011 .
b0 ;
1#
#346000
b1 (
#350000
0#
#355000
b111 0
b111 @
b0 /
b0 ?
b1101 5
b1101 >
b1100 D
b10001 C
b1101 -
b1101 F
b10110110 B
b1110 4
b1110 =
b11000 A
b1100 3
b1100 <
b10 9
b10 E
b10 :
b110 2
b10 1
b10 6
b100001110001100000100011011000000100011 "
b100001110001100000100011011000000100011 .
b1 ;
1#
#356000
b10 (
#360000
0#
#365000
b1111 5
b1111 >
b10 /
b10 ?
b1 D
b1111 -
b1111 F
b100 0
b100 @
b1111000 B
b1000 4
b1000 =
b11 9
b11 E
b10011 C
b11 :
b111 2
b11 1
b100 A
b11 3
b11 <
b11 6
b100001110001100000100011001000000100011 "
b100001110001100000100011001000000100011 .
b10 ;
1#
#366000
b11 (
#370000
0#
#375000
b10 /
b10 ?
b100 0
b100 @
b10011 C
b100 A
b1 5
b1 >
b1 D
b1 -
b1 F
b1 B
b1 4
b1 =
b0 9
b0 E
b0 :
b100 2
b0 1
b100 6
b100000001001100000100011001000000100011 "
b100000001001100000100011001000000100011 .
b11 ;
1#
#376000
b100 (
#380000
0#
#385000
b1000 0
b1000 @
b10 /
b10 ?
b1001 5
b1001 >
b11 D
b10011 C
b1001 -
b1001 F
b110110 B
b110 4
b110 =
b1000 A
b101 3
b101 <
b1 9
b1 E
b1 :
b101 2
b1 1
b101 6
b100000001001100000100011001000010100011 "
b100000001001100000100011001000010100011 .
b100 ;
1#
#386000
b101 (
#390000
0#
#395000
b1000 /
b1000 ?
b0 0
b0 @
b1101 5
b1101 >
b1000 C
b1101 -
b1101 F
b10001 A
b100 3
b100 <
b10 9
b10 E
b1101 D
b10 :
b110 2
b10 1
b1101 B
b1 4
b1 =
b110 6
b100000001010010000100011001000010100011 "
b100000001010010000100011001000010100011 .
b101 ;
1#
#396000
b110 (
#400000
0#
#405000
b1 /
b1 ?
b11 0
b11 @
b1111 5
b1111 >
b1 D
b10010 C
b1111 -
b1111 F
b1111000 B
b1000 4
b1000 =
b11 A
b10 3
b10 <
b11 9
b11 E
b11 :
b111 2
b11 1
b111 6
b100000001010010000100010001000010100011 "
b100000001010010000100010001000010100011 .
b110 ;
1#
#406000
b111 (
#410000
0#
#415000
b1000 0
b1000 @
b1111 /
b1111 ?
b1 5
b1 >
b1111 C
b1 -
b1 F
b1000 A
b11 3
b11 <
b0 9
b0 E
b101 D
b0 :
b1 2
b0 1
b101 B
b101 4
b101 =
b10 8
b1 7
b0 6
b11000001010010000100010001000010100011 "
b11000001010010000100010001000010100011 .
b111 ;
1#
#416000
b1000 (
#420000
0#
#425000
b110 0
b110 @
b10 /
b10 ?
b10 D
b10011 C
b11 2
b10 1
b10 B
b10 4
b10 =
b110 A
b100 3
b100 <
b1 6
b11000001010010000100010001000111101000 "
b11000001010010000100010001000111101000 .
1#
#426000
b1001 (
#430000
0#
#435000
b1010 0
b1010 @
b1001 /
b1001 ?
b1001 D
b1001 B
b1001 4
b1001 =
b1001 C
b101 2
b100 1
b1010 A
b1 3
b1 <
b10 6
b11000001010010000100010001100111101000 "
b11000001010010000100010001100111101000 .
1#
#436000
b1010 (
#440000
0#
#445000
b1100 /
b1100 ?
b110 D
b111 0
b111 @
b110 B
b110 4
b110 =
b1100 C
b111 2
b110 1
b111 A
b1 3
b1 <
b11 6
b11000001010010101000010001100111101000 "
b11000001010010101000010001100111101000 .
1#
#446000
b1011 (
#450000
0#
#455000
b1110 0
b1110 @
b10 /
b10 ?
b110 D
b10011 C
b10 2
b0 1
b110 B
b110 4
b110 =
b1110 A
b1000 3
b1000 <
b10 7
b0 6
b110000111010010101000010001100111101000 "
b110000111010010101000010001100111101000 .
1#
#456000
b1100 (
#460000
0#
#465000
b1101 5
b1101 >
b110 /
b110 ?
b1101 -
b1101 F
b111 0
b111 @
b10 9
b10 E
b1001 D
b10111 C
b10 :
b11 2
b1 1
b11010 B
b10 4
b10 =
b11000 A
b1111 3
b1111 <
b1 6
b110000111010010101000010000100111101110 "
b110000111010010101000010000100111101110 .
1#
#466000
b1101 (
#470000
0#
#475000
b1 5
b1 >
b11 /
b11 ?
b1 -
b1 F
b0 0
b0 @
b0 9
b0 E
b111 D
b10100 C
b0 :
b110 2
b100 1
b111 B
b111 4
b111 =
b10001 A
b1010 3
b1010 <
b10 6
b110000111010010101000110000100011101110 "
b110000111010010101000110000100011101110 .
1#
#476000
b1110 (
#480000
0#
#485000
b1101 5
b1101 >
b110 /
b110 ?
b1101 -
b1101 F
b1100 0
b1100 @
b10 9
b10 E
b11 D
b10111 C
b10 :
b111 2
b101 1
b10011100 B
b1100 4
b1100 =
b1100 A
b1001 3
b1001 <
b11 6
b110000011010010000000110000100011101110 "
b110000011010010000000110000100011101110 .
1#
#486000
b1111 (
#490000
0#
#495000
b1 5
b1 >
b1110 0
b1110 @
b1110 /
b1110 ?
b1 -
b1 F
b0 9
b0 E
b0 D
b11111 C
b0 :
b100 2
b0 1
b0 B
b0 4
b0 =
b1110 A
b1110 3
b1110 <
b11 7
b0 6
b11000011011000000000110000100011101110 "
b11000011011000000000110000100011101110 .
1#
#496000
b10000 (
#500000
0#
#505000
b1 /
b1 ?
b1101 0
b1101 @
b1001 5
b1001 >
b10010 C
b1001 -
b1001 F
b1101 A
b111 3
b111 <
b1 9
b1 E
b110 D
b1 :
b101 2
b1 1
b1101100 B
b1100 4
b1100 =
b1 6
b11000011011000111000110000100011101110 "
b11000011011000111000110000100011101110 .
1#
#506000
b10001 (
#510000
0#
#515000
b1101 5
b1101 >
b1110 /
b1110 ?
b1101 -
b1101 F
b111 0
b111 @
b10 9
b10 E
b101 D
b1110 C
b10 :
b110 2
b10 1
b100111 B
b11 4
b11 =
b111 A
b10 3
b10 <
b10 6
b11000011000010111000110000100110101110 "
b11000011000010111000110000100110101110 .
1#
#516000
b10010 (
#520000
0#
#525000
b1111 5
b1111 >
b1011 0
b1011 @
b1 /
b1 ?
b1111 -
b1111 F
b11 9
b11 E
b101 D
b10010 C
b11 :
b111 2
b11 1
b1011010 B
b110 4
b110 =
b1011 A
b110 3
b110 <
b11 6
b11001110000010111000110001110110101110 "
b11001110000010111000110001110110101110 .
1#
#526000
b10011 (
#530000
0#
#535000
b1 5
b1 >
b1011 0
b1011 @
b0 /
b0 ?
b1 -
b1 F
b0 9
b0 E
b1110 D
b10001 C
b0 :
b100 2
b0 1
b1110 B
b1110 4
b1110 =
b11100 A
b1110 3
b1110 <
b11 8
b0 6
b101110000010111001011001110110101110 "
b101110000010111001011001110110101110 .
1#
#536000
b10100 (
#540000
0#
#545000
b0 8
1!
1#
